{"entries": [{"from": 21.71, "until": 43.18, "speaker": "ellie", "text": "hi i am ellie thanks for coming in today i was created to talk to people in a safe and secure environment i am not a therapist but i am here to learn about people and would love to learn about you i will ask a few questions to get us started and please feel free to tell me anything your answers are totally confidential are you okay with this"}, {"from": 43.68, "until": 43.98, "speaker": "participant", "text": "sure"}, {"from": 44.85, "until": 46.93, "speaker": "ellie", "text": "so how are you doing today"}, {"from": 48.05, "until": 52.22, "speaker": "participant", "text": "i am fine tired i had to bike it here so my back is sweaty "}, {"from": 51.78, "until": 52.97, "speaker": "ellie", "text": "where are you from originally "}, {"from": 53.84, "until": 56.36, "speaker": "participant", "text": "i am from la"}, {"from": 58.06, "until": 60.08, "speaker": "ellie", "text": "what are some things you really like about la"}, {"from": 61.01, "until": 67.04, "speaker": "participant", "text": " the places there is to go there is always things to do here "}, {"from": 118.44, "until": 119.82, "speaker": "ellie", "text": "what do you do to relax"}, {"from": 120.66, "until": 124.45, "speaker": "participant", "text": "ride my bike make music sit at home watch movies"}, {"from": 125.89, "until": 128.05, "speaker": "ellie", "text": "what are some things that make you really mad"}, {"from": 132.36, "until": 137.54, "speaker": "participant", "text": "drivers people who gangsters i do not know "}, {"from": 138.67, "until": 140.1, "speaker": "ellie", "text": "what do you do when you are annoyed "}, {"from": 141.63, "until": 143.62, "speaker": "participant", "text": "go out ride my bike take a walk "}, {"from": 145.51, "until": 147.37, "speaker": "ellie", "text": "how are you at controlling your temper "}, {"from": 148.22, "until": 150.26, "speaker": "participant", "text": "pretty good i do not get angry very often "}, {"from": 151.34, "until": 154.37, "speaker": "ellie", "text": "when was the last time you argued with someone and what was it about "}, {"from": 155.42, "until": 171.32, "speaker": "participant", "text": " let is see h my girlfriend she did not wanna go to my friend is house and what happened what happened yeah that was it "}, {"from": 173.03, "until": 174.71, "speaker": "ellie", "text": "what are some things you like to do for fun "}, {"from": 176.0, "until": 185.93, "speaker": "participant", "text": " same thing make music ride my bike hang out with friends just normal kid stuff "}, {"from": 198.1, "until": 200.56, "speaker": "ellie", "text": "who is someone that is been a positive influence in your life"}, {"from": 201.64, "until": 208.94, "speaker": "participant", "text": " let is see i do not really know a bunch of people i guess i can not really pick one right now"}, {"from": 213.37, "until": 214.9, "speaker": "ellie", "text": "have you ever served in the military "}, {"from": 215.46, "until": 215.69, "speaker": "participant", "text": "nope"}, {"from": 216.69, "until": 218.61, "speaker": "ellie", "text": "have you ever been diagnosed with ptsd"}, {"from": 216.95, "until": 219.6, "speaker": "participant", "text": "i do not want to nope"}, {"from": 220.49, "until": 222.22, "speaker": "ellie", "text": "have you been diagnosed with depression "}, {"from": 223.67, "until": 224.52, "speaker": "participant", "text": "no "}, {"from": 225.08, "until": 227.43, "speaker": "ellie", "text": "how easy is it for you to get a good night is sleep "}, {"from": 228.28, "until": 240.64, "speaker": "participant", "text": " i mean i usually just stay up pretty late so i usually my fault that i do not go to sleep early and then i wake up really late in the afternoon so"}, {"from": 241.74, "until": 243.43, "speaker": "ellie", "text": "what are you like when you do not sleep well "}, {"from": 241.75, "until": 253.19, "speaker": "participant", "text": "kind of hard the same just a little drowsy tend to go to sleep earlier nothing i am still active i do not really change"}, {"from": 254.55, "until": 255.95, "speaker": "ellie", "text": "how have you been feeling lately "}, {"from": 256.87, "until": 262.11, "speaker": "participant", "text": " fine happy normal just "}, {"from": 262.65, "until": 265.06, "speaker": "ellie", "text": "when was the last time you felt really happy "}, {"from": 262.7, "until": 277.49, "speaker": "participant", "text": "same my birthday that was two days ago two three days ago i got some i got a gift from my girlfriend it was pretty cool "}]}