{"entries": [{"from": 366.94199999999995, "until": 374.785, "speaker": "ellie", "text": "okay tell me about an event or something that you wish you could erase from your memory"}, {"from": 378.38, "until": 387.15, "speaker": "participant", "text": "well i do not think i have anything that bad that i want to erase from my memory i can not think of any sorry "}, {"from": 387.23800000000006, "until": 391.836, "speaker": "ellie", "text": "okay what is something you feel guilty about"}, {"from": 395.01, "until": 408.11, "speaker": "participant", "text": "guilty about i do not think i have anything to feel guilty about however sometimes i feel guilty when i eat a lot of cookies cause that is not good for my health "}, {"from": 409.287, "until": 413.369, "speaker": "ellie", "text": "okay how easy is it for you to get a good night is sleep"}, {"from": 414.34, "until": 419.48, "speaker": "participant", "text": "very easy i sleep like a baby once i hit the bed "}, {"from": 419.347, "until": 423.19, "speaker": "ellie", "text": "that is good how have you been feeling lately"}, {"from": 424.49, "until": 426.11, "speaker": "participant", "text": "i have been feeling good"}, {"from": 427.316, "until": 430.486, "speaker": "ellie", "text": "have you noticed any changes in your behavior or thoughts lately"}, {"from": 431.28, "until": 432.04, "speaker": "participant", "text": "no"}, {"from": 477.371, "until": 478.441, "speaker": "ellie", "text": "is there anything you regret"}, {"from": 480.03, "until": 481.99, "speaker": "participant", "text": " not that i know of no"}, {"from": 483.166, "until": 486.116, "speaker": "ellie", "text": "what advice would you give to yourself ten or twenty years ago"}, {"from": 488.0, "until": 499.95, "speaker": "participant", "text": "oh always do what you want to do life is short and always keep on learning"}, {"from": 502.44800000000004, "until": 505.333, "speaker": "ellie", "text": "what are some things you wish you could change about yourself"}, {"from": 507.5, "until": 510.72, "speaker": "participant", "text": " i want to lose two more pounds"}, {"from": 513.107, "until": 522.047, "speaker": "ellie", "text": "okay tell me about a time when someone made you feel really badly about yourself"}, {"from": 522.56, "until": 534.24, "speaker": "participant", "text": "i i have been very very blessed i have never really felt anyone make me feel bad and i usually interact well with everyone i meet and i am very blessed to have everyone be nice to me"}, {"from": 535.594, "until": 541.707, "speaker": "ellie", "text": "that is great what would you say are some of your best qualities"}, {"from": 543.26, "until": 561.45, "speaker": "participant", "text": "i am a great listener i spend quality time with my friends and family not quantity necessarily but quality time and i am very supportive and i love to pretty much listen listen and listen sometimes that is all people need"}]}