{"entries": [{"from": 210.00099999999998, "until": 221.762, "speaker": "ellie", "text": "sometimes when i am feeling tense i turn on the fish tank screensaver hey i know it is not hawaii but it is the best i have got what do you do to relax"}, {"from": 224.79, "until": 230.69, "speaker": "participant", "text": "h i just try and and just meditate"}, {"from": 233.144, "until": 234.084, "speaker": "ellie", "text": "how hard is that"}, {"from": 235.59, "until": 236.48, "speaker": "participant", "text": "it is not easy"}, {"from": 239.824, "until": 243.90599999999998, "speaker": "ellie", "text": "okay how are you at controlling your temper"}, {"from": 246.04, "until": 249.91, "speaker": "participant", "text": "oh not not real good at it but i do not get angry too often"}, {"from": 251.676, "until": 253.15599999999998, "speaker": "ellie", "text": "has that gotten you in trouble"}, {"from": 254.68, "until": 256.31, "speaker": "participant", "text": "actually i think it has yes"}, {"from": 257.43, "until": 258.59, "speaker": "ellie", "text": "can you tell me about that"}, {"from": 259.76, "until": 269.03, "speaker": "participant", "text": "oh work situations where you get mad angry with another employee and you should be more cool and calm"}, {"from": 267.434, "until": 277.14, "speaker": "ellie", "text": " i see i see when was the last time you argued with someone and what was it about"}, {"from": 279.85, "until": 295.315, "speaker": "participant", "text": "oh several days a few days ago it was about somebody is excessive drinking and and money not my drinking some"}, {"from": 294.454, "until": 295.994, "speaker": "ellie", "text": "how did you feel in that moment"}, {"from": 297.45, "until": 302.19, "speaker": "participant", "text": "frustrated person was not able to listen very easily"}, {"from": 304.731, "until": 310.908, "speaker": "ellie", "text": "okay tell me about a situation that you wish you had handled differently"}, {"from": 317.495, "until": 328.3, "speaker": "participant", "text": "well stuff that xxx dating back twenty years ago things in my marriage maybe arguing or being difficult"}, {"from": 331.162, "until": 333.032, "speaker": "ellie", "text": "could you have done anything to avoid it"}, {"from": 335.45, "until": 341.91, "speaker": "participant", "text": "sure i could have i could have been more mindful in certain situations"}, {"from": 344.851, "until": 348.45099999999996, "speaker": "ellie", "text": "tell me about the hardest decision you have ever had to make"}, {"from": 355.15, "until": 361.795, "speaker": "participant", "text": "one of them was whether or not i was should get married when i was much younger"}, {"from": 363.394, "until": 364.824, "speaker": "ellie", "text": "what made you decide to do that"}, {"from": 368.72, "until": 374.24, "speaker": "participant", "text": " i did not wanna disappoint my fiancee my girlfriend she wanted to get married so i did not wanna hurt her feelings"}, {"from": 376.18300000000005, "until": 377.18300000000005, "speaker": "ellie", "text": "are you happy you did that"}, {"from": 378.225, "until": 378.695, "speaker": "participant", "text": "yes"}, {"from": 381.015, "until": 387.339, "speaker": "ellie", "text": "that is good tell me about a situation that you wish you had handled differently"}, {"from": 389.605, "until": 391.645, "speaker": "participant", "text": "i think i did that did not i "}, {"from": 565.03, "until": 565.6, "speaker": "ellie", "text": "why"}, {"from": 567.38, "until": 572.3, "speaker": "participant", "text": "can not fall asleep and when i do i wake up a lot after an hour or two"}, {"from": 573.826, "until": 575.206, "speaker": "ellie", "text": "are they triggered by something"}, {"from": 576.48, "until": 588.39, "speaker": "participant", "text": " stress maybe maybe just old age i am not sure i looked it up on the internet it says old people do not really sleep very well once you reach my age"}, {"from": 587.207, "until": 592.6619999999998, "speaker": "ellie", "text": " laughter what are you like when you do not sleep well"}, {"from": 597.28, "until": 607.81, "speaker": "participant", "text": "i do not know i feel i do not feel right i feel tired depressed not well rested"}, {"from": 609.018, "until": 611.563, "speaker": "ellie", "text": " how have you been feeling lately"}, {"from": 614.35, "until": 620.98, "speaker": "participant", "text": "been very anxious and stressed out somewhat sad more than somewhat i have been sad lately"}, {"from": 622.4540000000002, "until": 626.165, "speaker": "ellie", "text": "i am sorry can you tell me about that"}, {"from": 628.83, "until": 646.27, "speaker": "participant", "text": "well i am not working right now i have a lot of pressures things do not seem to be going right i am getting a lot of things seem seem to be not working out i am getting a lot of bad news things are not going my way sometimes always"}, {"from": 646.229, "until": 646.679, "speaker": "ellie", "text": "h"}, {"from": 647.55, "until": 647.98, "speaker": "participant", "text": "lately"}, {"from": 647.987, "until": 650.197, "speaker": "ellie", "text": "it can be tough to find a good job these days"}, {"from": 651.73, "until": 652.41, "speaker": "participant", "text": "yeah i agree"}, {"from": 654.65, "until": 656.69, "speaker": "ellie", "text": "have you ever been diagnosed with ptsd"}, {"from": 657.15, "until": 657.77, "speaker": "participant", "text": "no i have not"}, {"from": 658.596, "until": 660.4060000000002, "speaker": "ellie", "text": "have you been diagnosed with depression"}, {"from": 660.89, "until": 664.57, "speaker": "participant", "text": " depression or sadness i would say yes"}, {"from": 665.416, "until": 667.336, "speaker": "ellie", "text": "how long ago were you diagnosed"}, {"from": 668.78, "until": 674.21, "speaker": "participant", "text": "well i do not know if it is a diagnosis i xxx thirty years ago xxx thirty five years ago"}, {"from": 675.222, "until": 676.572, "speaker": "ellie", "text": "what got you to seek help"}, {"from": 679.02, "until": 685.64, "speaker": "participant", "text": "wanting to improve my life wanting to be the best person i can be wanting to be happy"}]}